idcode/__init__.py
idcode/cli.py
idcode/core_values.py
idcode/custom_encoding.py
idcode/interactive_decoder.py
idcode/preprocessing.py
idcode-0.2.0.dist-info/entry_points.txt
idcode-0.2.0.dist-info/LICENSE
idcode-0.2.0.dist-info/WHEEL
idcode-0.2.0.dist-info/METADATA
idcode-0.2.0.dist-info/RECORD
